mcp_tomi_scraper/__init__.py
mcp_tomi_scraper/main.py
mcp_tomi_scraper/product_search.py
mcp_tomi_scraper/tomi_login_state.json
mcp_tomi_scraper-0.1.1.dist-info/METADATA
mcp_tomi_scraper-0.1.1.dist-info/WHEEL
mcp_tomi_scraper-0.1.1.dist-info/entry_points.txt
mcp_tomi_scraper-0.1.1.dist-info/top_level.txt
mcp_tomi_scraper-0.1.1.dist-info/RECORD
