Metadata-Version: 2.4
Name: mcp-tomi-scraper
Version: 0.1.1
Summary: An MCP server for scraping tomi.com product data
Author-email: dubdoo <yu-yy21@qq.com>
Requires-Python: >=3.9
Requires-Dist: playwright>=1.40.0
Requires-Dist: jsonrpc>=1.13.5
